.gitignore
CHANGES.txt
CONTRIBUTORS.txt
MANIFEST.in
README.rst
bootstrap.py
buildout.cfg
setup.py
collective/__init__.py
collective.js.highslide.egg-info/PKG-INFO
collective.js.highslide.egg-info/SOURCES.txt
collective.js.highslide.egg-info/dependency_links.txt
collective.js.highslide.egg-info/entry_points.txt
collective.js.highslide.egg-info/namespace_packages.txt
collective.js.highslide.egg-info/not-zip-safe
collective.js.highslide.egg-info/requires.txt
collective.js.highslide.egg-info/top_level.txt
collective/js/__init__.py
collective/js/highslide/__init__.py
collective/js/highslide/configure.zcml
collective/js/highslide/interfaces.py
collective/js/highslide/profiles/default/browserlayer.xml
collective/js/highslide/profiles/default/cssregistry.xml
collective/js/highslide/profiles/default/jsregistry.xml
collective/js/highslide/profiles/default/metadata.xml
collective/js/highslide/resources/highslide-full.js
collective/js/highslide/resources/highslide-ie6.css
collective/js/highslide/resources/highslide-with-gallery.js
collective/js/highslide/resources/highslide-with-html.js
collective/js/highslide/resources/highslide.css
collective/js/highslide/resources/highslide.js
collective/js/highslide/resources/graphics/close.png
collective/js/highslide/resources/graphics/closeX.png
collective/js/highslide/resources/graphics/controlbar-black-border.gif
collective/js/highslide/resources/graphics/controlbar-text-buttons.png
collective/js/highslide/resources/graphics/controlbar-white-small.gif
collective/js/highslide/resources/graphics/controlbar-white.gif
collective/js/highslide/resources/graphics/controlbar2.gif
collective/js/highslide/resources/graphics/controlbar3.gif
collective/js/highslide/resources/graphics/controlbar4-hover.gif
collective/js/highslide/resources/graphics/controlbar4.gif
collective/js/highslide/resources/graphics/fullexpand.gif
collective/js/highslide/resources/graphics/geckodimmer.png
collective/js/highslide/resources/graphics/icon.gif
collective/js/highslide/resources/graphics/loader.gif
collective/js/highslide/resources/graphics/loader.white.gif
collective/js/highslide/resources/graphics/resize.gif
collective/js/highslide/resources/graphics/scrollarrows.png
collective/js/highslide/resources/graphics/zoomin.cur
collective/js/highslide/resources/graphics/zoomout.cur
collective/js/highslide/resources/graphics/outlines/Outlines.psd
